{
  "primitives": {
    "color": {
      "blue": {
        "50": {
          "value": "#e0f9ff",
          "type": "color",
          "$extensions": {
            "com.figma.scopes": [
              "ALL_SCOPES"
            ]
          }
        },
        "100": {
          "value": "#b3f0ff",
          "type": "color",
          "$extensions": {
            "com.figma.scopes": [
              "ALL_SCOPES"
            ]
          }
        },
        "200": {
          "value": "#66e2ff",
          "type": "color",
          "$extensions": {
            "com.figma.scopes": [
              "ALL_SCOPES"
            ]
          }
        },
        "300": {
          "value": "#00d4ff",
          "type": "color",
          "$extensions": {
            "com.figma.scopes": [
              "ALL_SCOPES"
            ]
          }
        },
        "400": {
          "value": "#00bfea",
          "type": "color",
          "$extensions": {
            "com.figma.scopes": [
              "ALL_SCOPES"
            ]
          }
        },
        "500": {
          "value": "#0099cc",
          "type": "color",
          "$extensions": {
            "com.figma.scopes": [
              "ALL_SCOPES"
            ]
          }
        },
        "600": {
          "value": "#0077a8",
          "type": "color",
          "$extensions": {
            "com.figma.scopes": [
              "ALL_SCOPES"
            ]
          }
        },
        "700": {
          "value": "#005580",
          "type": "color",
          "$extensions": {
            "com.figma.scopes": [
              "ALL_SCOPES"
            ]
          }
        },
        "800": {
          "value": "#003d5c",
          "type": "color",
          "$extensions": {
            "com.figma.scopes": [
              "ALL_SCOPES"
            ]
          }
        },
        "900": {
          "value": "#001a2e",
          "type": "color",
          "$extensions": {
            "com.figma.scopes": [
              "ALL_SCOPES"
            ]
          }
        },
        "950": {
          "value": "#001220",
          "type": "color",
          "$extensions": {
            "com.figma.scopes": [
              "ALL_SCOPES"
            ]
          }
        }
      },
      "neutral": {
        "0": {
          "value": "#FFFFFF",
          "type": "color"
        },
        "50": {
          "value": "#F8FAFC",
          "type": "color"
        },
        "100": {
          "value": "#F1F5F9",
          "type": "color"
        },
        "200": {
          "value": "#E2E8F0",
          "type": "color"
        },
        "300": {
          "value": "#CBD5E1",
          "type": "color"
        },
        "400": {
          "value": "#94A3B8",
          "type": "color"
        },
        "500": {
          "value": "#64748B",
          "type": "color"
        },
        "600": {
          "value": "#475569",
          "type": "color"
        },
        "700": {
          "value": "#334155",
          "type": "color"
        },
        "800": {
          "value": "#1C1C26",
          "type": "color"
        },
        "900": {
          "value": "#13131A",
          "type": "color"
        },
        "950": {
          "value": "#0A0A0F",
          "type": "color"
        }
      },
      "green": {
        "500": {
          "value": "#22c55e",
          "type": "color",
          "$extensions": {
            "com.figma.scopes": [
              "ALL_SCOPES"
            ]
          }
        }
      },
      "amber": {
        "500": {
          "value": "#f59e0b",
          "type": "color",
          "$extensions": {
            "com.figma.scopes": [
              "ALL_SCOPES"
            ]
          }
        }
      },
      "red": {
        "500": {
          "value": "#ef4444",
          "type": "color",
          "$extensions": {
            "com.figma.scopes": [
              "ALL_SCOPES"
            ]
          }
        }
      }
    },
    "typography": {
      "fontFamily": {
        "display": {
          "value": "Barlow Condensed",
          "type": "text",
          "$extensions": {
            "com.figma.scopes": [
              "ALL_SCOPES"
            ]
          }
        },
        "body": {
          "value": "Inter",
          "type": "text",
          "$extensions": {
            "com.figma.scopes": [
              "ALL_SCOPES"
            ]
          }
        },
        "mono": {
          "value": "JetBrains Mono",
          "type": "text",
          "$extensions": {
            "com.figma.scopes": [
              "ALL_SCOPES"
            ]
          }
        }
      },
      "fontSize": {
        "10": {
          "value": "10",
          "type": "fontSizes",
          "$extensions": {
            "com.figma.scopes": [
              "FONT_SIZE"
            ]
          }
        },
        "11": {
          "value": "11",
          "type": "fontSizes",
          "$extensions": {
            "com.figma.scopes": [
              "FONT_SIZE"
            ]
          }
        },
        "12": {
          "value": "12",
          "type": "fontSizes",
          "$extensions": {
            "com.figma.scopes": [
              "FONT_SIZE"
            ]
          }
        },
        "13": {
          "value": "13",
          "type": "fontSizes",
          "$extensions": {
            "com.figma.scopes": [
              "FONT_SIZE"
            ]
          }
        },
        "14": {
          "value": "14",
          "type": "fontSizes",
          "$extensions": {
            "com.figma.scopes": [
              "FONT_SIZE"
            ]
          }
        },
        "16": {
          "value": "16",
          "type": "fontSizes",
          "$extensions": {
            "com.figma.scopes": [
              "FONT_SIZE"
            ]
          }
        },
        "18": {
          "value": "18",
          "type": "fontSizes",
          "$extensions": {
            "com.figma.scopes": [
              "FONT_SIZE"
            ]
          }
        },
        "20": {
          "value": "20",
          "type": "fontSizes",
          "$extensions": {
            "com.figma.scopes": [
              "FONT_SIZE"
            ]
          }
        },
        "24": {
          "value": "24",
          "type": "fontSizes",
          "$extensions": {
            "com.figma.scopes": [
              "FONT_SIZE"
            ]
          }
        },
        "28": {
          "value": "28",
          "type": "fontSizes",
          "$extensions": {
            "com.figma.scopes": [
              "FONT_SIZE"
            ]
          }
        },
        "32": {
          "value": "32",
          "type": "fontSizes",
          "$extensions": {
            "com.figma.scopes": [
              "FONT_SIZE"
            ]
          }
        },
        "36": {
          "value": "36",
          "type": "fontSizes",
          "$extensions": {
            "com.figma.scopes": [
              "FONT_SIZE"
            ]
          }
        },
        "48": {
          "value": "48",
          "type": "fontSizes",
          "$extensions": {
            "com.figma.scopes": [
              "FONT_SIZE"
            ]
          }
        },
        "64": {
          "value": "64",
          "type": "fontSizes",
          "$extensions": {
            "com.figma.scopes": [
              "FONT_SIZE"
            ]
          }
        }
      },
      "fontWeight": {
        "regular": {
          "value": "400",
          "type": "fontWeights",
          "$extensions": {
            "com.figma.scopes": [
              "FONT_WEIGHT"
            ]
          }
        },
        "medium": {
          "value": "500",
          "type": "fontWeights",
          "$extensions": {
            "com.figma.scopes": [
              "FONT_WEIGHT"
            ]
          }
        },
        "semiBold": {
          "value": "600",
          "type": "fontWeights",
          "$extensions": {
            "com.figma.scopes": [
              "FONT_WEIGHT"
            ]
          }
        },
        "bold": {
          "value": "700",
          "type": "fontWeights",
          "$extensions": {
            "com.figma.scopes": [
              "FONT_WEIGHT"
            ]
          }
        },
        "extraBold": {
          "value": "800",
          "type": "fontWeights",
          "$extensions": {
            "com.figma.scopes": [
              "FONT_WEIGHT"
            ]
          }
        }
      },
      "lineHeight": {
        "none": {
          "value": "1",
          "type": "lineHeights",
          "$extensions": {
            "com.figma.scopes": [
              "LINE_HEIGHT"
            ]
          }
        },
        "tight": {
          "value": "1.1",
          "type": "lineHeights",
          "$extensions": {
            "com.figma.scopes": [
              "LINE_HEIGHT"
            ]
          }
        },
        "snug": {
          "value": "1.25",
          "type": "lineHeights",
          "$extensions": {
            "com.figma.scopes": [
              "LINE_HEIGHT"
            ]
          }
        },
        "normal": {
          "value": "1.5",
          "type": "lineHeights",
          "$extensions": {
            "com.figma.scopes": [
              "LINE_HEIGHT"
            ]
          }
        },
        "relaxed": {
          "value": "1.625",
          "type": "lineHeights",
          "$extensions": {
            "com.figma.scopes": [
              "LINE_HEIGHT"
            ]
          }
        }
      },
      "letterSpacing": {
        "tight": {
          "value": "-0.02",
          "type": "letterSpacing",
          "$extensions": {
            "com.figma.scopes": [
              "LETTER_SPACING"
            ]
          }
        },
        "normal": {
          "value": "0",
          "type": "letterSpacing",
          "$extensions": {
            "com.figma.scopes": [
              "LETTER_SPACING"
            ]
          }
        },
        "wide": {
          "value": "0.05",
          "type": "letterSpacing",
          "$extensions": {
            "com.figma.scopes": [
              "LETTER_SPACING"
            ]
          }
        },
        "wider": {
          "value": "0.1",
          "type": "letterSpacing",
          "$extensions": {
            "com.figma.scopes": [
              "LETTER_SPACING"
            ]
          }
        },
        "widest": {
          "value": "0.15",
          "type": "letterSpacing",
          "$extensions": {
            "com.figma.scopes": [
              "LETTER_SPACING"
            ]
          }
        }
      }
    },
    "spacing": {
      "0": {
        "value": "0",
        "type": "spacing",
        "$extensions": {
          "com.figma.scopes": [
            "ALL_SCOPES"
          ]
        }
      },
      "1": {
        "value": "2",
        "type": "spacing",
        "$extensions": {
          "com.figma.scopes": [
            "ALL_SCOPES"
          ]
        }
      },
      "2": {
        "value": "4",
        "type": "spacing",
        "$extensions": {
          "com.figma.scopes": [
            "ALL_SCOPES"
          ]
        }
      },
      "3": {
        "value": "8",
        "type": "spacing",
        "$extensions": {
          "com.figma.scopes": [
            "ALL_SCOPES"
          ]
        }
      },
      "4": {
        "value": "12",
        "type": "spacing",
        "$extensions": {
          "com.figma.scopes": [
            "ALL_SCOPES"
          ]
        }
      },
      "5": {
        "value": "16",
        "type": "spacing",
        "$extensions": {
          "com.figma.scopes": [
            "ALL_SCOPES"
          ]
        }
      },
      "6": {
        "value": "20",
        "type": "spacing",
        "$extensions": {
          "com.figma.scopes": [
            "ALL_SCOPES"
          ]
        }
      },
      "7": {
        "value": "24",
        "type": "spacing",
        "$extensions": {
          "com.figma.scopes": [
            "ALL_SCOPES"
          ]
        }
      },
      "8": {
        "value": "32",
        "type": "spacing",
        "$extensions": {
          "com.figma.scopes": [
            "ALL_SCOPES"
          ]
        }
      },
      "9": {
        "value": "40",
        "type": "spacing",
        "$extensions": {
          "com.figma.scopes": [
            "ALL_SCOPES"
          ]
        }
      },
      "10": {
        "value": "48",
        "type": "spacing",
        "$extensions": {
          "com.figma.scopes": [
            "ALL_SCOPES"
          ]
        }
      },
      "11": {
        "value": "64",
        "type": "spacing",
        "$extensions": {
          "com.figma.scopes": [
            "ALL_SCOPES"
          ]
        }
      },
      "12": {
        "value": "80",
        "type": "spacing",
        "$extensions": {
          "com.figma.scopes": [
            "ALL_SCOPES"
          ]
        }
      }
    },
    "radius": {
      "0": {
        "value": "0",
        "type": "borderRadius",
        "$extensions": {
          "com.figma.scopes": [
            "CORNER_RADIUS"
          ]
        }
      },
      "1": {
        "value": "2",
        "type": "borderRadius",
        "$extensions": {
          "com.figma.scopes": [
            "CORNER_RADIUS"
          ]
        }
      },
      "2": {
        "value": "4",
        "type": "borderRadius",
        "$extensions": {
          "com.figma.scopes": [
            "CORNER_RADIUS"
          ]
        }
      },
      "3": {
        "value": "8",
        "type": "borderRadius",
        "$extensions": {
          "com.figma.scopes": [
            "CORNER_RADIUS"
          ]
        }
      },
      "4": {
        "value": "12",
        "type": "borderRadius",
        "$extensions": {
          "com.figma.scopes": [
            "CORNER_RADIUS"
          ]
        }
      },
      "5": {
        "value": "16",
        "type": "borderRadius",
        "$extensions": {
          "com.figma.scopes": [
            "CORNER_RADIUS"
          ]
        }
      },
      "6": {
        "value": "20",
        "type": "borderRadius",
        "$extensions": {
          "com.figma.scopes": [
            "CORNER_RADIUS"
          ]
        }
      },
      "7": {
        "value": "24",
        "type": "borderRadius",
        "$extensions": {
          "com.figma.scopes": [
            "CORNER_RADIUS"
          ]
        }
      },
      "8": {
        "value": "32",
        "type": "borderRadius",
        "$extensions": {
          "com.figma.scopes": [
            "CORNER_RADIUS"
          ]
        }
      },
      "full": {
        "value": "9999",
        "type": "borderRadius",
        "$extensions": {
          "com.figma.scopes": [
            "CORNER_RADIUS"
          ]
        }
      }
    },
    "$extensions": {
      "studio": {
        "tokens": {
          "version": {
            "value": "1.0",
            "type": "other"
          },
          "figma": {
            "collection": {
              "value": "Primitives",
              "type": "other"
            }
          }
        }
      }
    }
  },
  "semantic": {
    "color": {
      "background": {
        "bg-base": {
          "value": "{color.neutral.950}",
          "type": "color",
          "$extensions": {
            "com.figma.scopes": [
              "ALL_SCOPES"
            ]
          }
        },
        "bg-surface": {
          "value": "{color.neutral.900}",
          "type": "color",
          "$extensions": {
            "com.figma.scopes": [
              "ALL_SCOPES"
            ]
          }
        },
        "bg-elevated": {
          "value": "{color.neutral.800}",
          "type": "color",
          "$extensions": {
            "com.figma.scopes": [
              "ALL_SCOPES"
            ]
          }
        }
      },
      "brand": {
        "brand-primary": {
          "value": "{color.blue.300}",
          "type": "color",
          "$extensions": {
            "com.figma.scopes": [
              "ALL_SCOPES"
            ]
          }
        },
        "brand-secondary": {
          "value": "{color.blue.500}",
          "type": "color",
          "$extensions": {
            "com.figma.scopes": [
              "ALL_SCOPES"
            ]
          }
        }
      },
      "text": {
        "text-primary": {
          "value": "{color.neutral.50}",
          "type": "color",
          "$extensions": {
            "com.figma.scopes": [
              "ALL_SCOPES"
            ]
          }
        },
        "text-secondary": {
          "value": "{color.neutral.400}",
          "type": "color",
          "$extensions": {
            "com.figma.scopes": [
              "ALL_SCOPES"
            ]
          }
        },
        "text-muted": {
          "value": "{color.neutral.600}",
          "type": "color",
          "$extensions": {
            "com.figma.scopes": [
              "ALL_SCOPES"
            ]
          }
        }
      },
      "status": {
        "success": {
          "value": "{color.green.500}",
          "type": "color",
          "$extensions": {
            "com.figma.scopes": [
              "ALL_SCOPES"
            ]
          }
        },
        "warning": {
          "value": "{color.amber.500}",
          "type": "color",
          "$extensions": {
            "com.figma.scopes": [
              "ALL_SCOPES"
            ]
          }
        },
        "error": {
          "value": "{color.red.500}",
          "type": "color",
          "$extensions": {
            "com.figma.scopes": [
              "ALL_SCOPES"
            ]
          }
        }
      }
    },
    "spacing": {
      "space-px": {
        "value": "{spacing.1}",
        "type": "spacing",
        "$extensions": {
          "com.figma.scopes": [
            "ALL_SCOPES"
          ]
        }
      },
      "space-1": {
        "value": "{spacing.2}",
        "type": "spacing",
        "$extensions": {
          "com.figma.scopes": [
            "ALL_SCOPES"
          ]
        }
      },
      "space-2": {
        "value": "{spacing.3}",
        "type": "spacing",
        "$extensions": {
          "com.figma.scopes": [
            "ALL_SCOPES"
          ]
        }
      },
      "space-3": {
        "value": "{spacing.4}",
        "type": "spacing",
        "$extensions": {
          "com.figma.scopes": [
            "ALL_SCOPES"
          ]
        }
      },
      "space-4": {
        "value": "{spacing.5}",
        "type": "spacing",
        "$extensions": {
          "com.figma.scopes": [
            "ALL_SCOPES"
          ]
        }
      },
      "space-5": {
        "value": "{spacing.6}",
        "type": "spacing",
        "$extensions": {
          "com.figma.scopes": [
            "ALL_SCOPES"
          ]
        }
      },
      "space-6": {
        "value": "{spacing.7}",
        "type": "spacing",
        "$extensions": {
          "com.figma.scopes": [
            "ALL_SCOPES"
          ]
        }
      },
      "space-8": {
        "value": "{spacing.8}",
        "type": "spacing",
        "$extensions": {
          "com.figma.scopes": [
            "ALL_SCOPES"
          ]
        }
      },
      "space-10": {
        "value": "{spacing.9}",
        "type": "spacing",
        "$extensions": {
          "com.figma.scopes": [
            "ALL_SCOPES"
          ]
        }
      },
      "space-12": {
        "value": "{spacing.10}",
        "type": "spacing",
        "$extensions": {
          "com.figma.scopes": [
            "ALL_SCOPES"
          ]
        }
      },
      "space-16": {
        "value": "{spacing.11}",
        "type": "spacing",
        "$extensions": {
          "com.figma.scopes": [
            "ALL_SCOPES"
          ]
        }
      },
      "space-20": {
        "value": "{spacing.space-12}",
        "type": "spacing",
        "$extensions": {
          "com.figma.scopes": [
            "ALL_SCOPES"
          ]
        }
      },
      "screen-horizontal": {
        "value": "{spacing.space-4}",
        "type": "spacing",
        "$extensions": {
          "com.figma.scopes": [
            "ALL_SCOPES"
          ]
        }
      },
      "screen-vertical": {
        "value": "{spacing.space-6}",
        "type": "spacing",
        "$extensions": {
          "com.figma.scopes": [
            "ALL_SCOPES"
          ]
        }
      },
      "card-padding": {
        "value": "{spacing.space-4}",
        "type": "spacing",
        "$extensions": {
          "com.figma.scopes": [
            "ALL_SCOPES"
          ]
        }
      },
      "card-gap": {
        "value": "{spacing.space-3}",
        "type": "spacing",
        "$extensions": {
          "com.figma.scopes": [
            "ALL_SCOPES"
          ]
        }
      },
      "section-gap": {
        "value": "{spacing.space-8}",
        "type": "spacing",
        "$extensions": {
          "com.figma.scopes": [
            "ALL_SCOPES"
          ]
        }
      },
      "list-item-gap": {
        "value": "{spacing.space-2}",
        "type": "spacing",
        "$extensions": {
          "com.figma.scopes": [
            "ALL_SCOPES"
          ]
        }
      },
      "icon-gap": {
        "value": "{spacing.space-2}",
        "type": "spacing",
        "$extensions": {
          "com.figma.scopes": [
            "ALL_SCOPES"
          ]
        }
      },
      "nav-height": {
        "value": "{spacing.space-20}",
        "type": "spacing",
        "$extensions": {
          "com.figma.scopes": [
            "ALL_SCOPES"
          ]
        }
      }
    },
    "radius": {
      "radius-none": {
        "value": "{radius.0}",
        "type": "borderRadius",
        "$extensions": {
          "com.figma.scopes": [
            "ALL_SCOPES"
          ]
        }
      },
      "radius-xs": {
        "value": "{radius.1}",
        "type": "borderRadius",
        "$extensions": {
          "com.figma.scopes": [
            "ALL_SCOPES"
          ]
        }
      },
      "radius-sm": {
        "value": "{radius.2}",
        "type": "borderRadius",
        "$extensions": {
          "com.figma.scopes": [
            "ALL_SCOPES"
          ]
        }
      },
      "radius-md": {
        "value": "{radius.3}",
        "type": "borderRadius",
        "$extensions": {
          "com.figma.scopes": [
            "ALL_SCOPES"
          ]
        }
      },
      "radius-lg": {
        "value": "{radius.4}",
        "type": "borderRadius",
        "$extensions": {
          "com.figma.scopes": [
            "ALL_SCOPES"
          ]
        }
      },
      "radius-xl": {
        "value": "{radius.5}",
        "type": "borderRadius",
        "$extensions": {
          "com.figma.scopes": [
            "ALL_SCOPES"
          ]
        }
      },
      "radius-2xl": {
        "value": "{radius.6}",
        "type": "borderRadius",
        "$extensions": {
          "com.figma.scopes": [
            "ALL_SCOPES"
          ]
        }
      },
      "radius-3xl": {
        "value": "{radius.7}",
        "type": "borderRadius",
        "$extensions": {
          "com.figma.scopes": [
            "ALL_SCOPES"
          ]
        }
      },
      "radius-4xl": {
        "value": "{radius.8}",
        "type": "borderRadius",
        "$extensions": {
          "com.figma.scopes": [
            "ALL_SCOPES"
          ]
        }
      },
      "radius-full": {
        "value": "{radius.full}",
        "type": "borderRadius",
        "$extensions": {
          "com.figma.scopes": [
            "ALL_SCOPES"
          ]
        }
      },
      "button-sm": {
        "value": "{radius.radius-sm}",
        "type": "borderRadius",
        "$extensions": {
          "com.figma.scopes": [
            "ALL_SCOPES"
          ]
        }
      },
      "button-md": {
        "value": "{radius.3}",
        "type": "borderRadius",
        "$extensions": {
          "com.figma.scopes": [
            "ALL_SCOPES"
          ]
        }
      },
      "card-sm": {
        "value": "{radius.radius-md}",
        "type": "borderRadius",
        "$extensions": {
          "com.figma.scopes": [
            "ALL_SCOPES"
          ]
        }
      },
      "card-lg": {
        "value": "{radius.radius-lg}",
        "type": "borderRadius",
        "$extensions": {
          "com.figma.scopes": [
            "ALL_SCOPES"
          ]
        }
      },
      "input": {
        "value": "{radius.radius-md}",
        "type": "borderRadius",
        "$extensions": {
          "com.figma.scopes": [
            "ALL_SCOPES"
          ]
        }
      },
      "modal": {
        "value": "{radius.radius-xl}",
        "type": "borderRadius",
        "$extensions": {
          "com.figma.scopes": [
            "ALL_SCOPES"
          ]
        }
      },
      "avatar": {
        "value": "{radius.radius-full}",
        "type": "borderRadius",
        "$extensions": {
          "com.figma.scopes": [
            "ALL_SCOPES"
          ]
        }
      },
      "badge": {
        "value": "{radius.radius-full}",
        "type": "borderRadius",
        "$extensions": {
          "com.figma.scopes": [
            "ALL_SCOPES"
          ]
        }
      },
      "tab": {
        "value": "{radius.radius-sm}",
        "type": "borderRadius",
        "$extensions": {
          "com.figma.scopes": [
            "ALL_SCOPES"
          ]
        }
      }
    },
    "typography": {
      "label": {
        "lg": {
          "fontSize": {
            "value": "{typography.fontSize.16}",
            "type": "fontSizes"
          },
          "lineHeight": {
            "value": "{typography.lineHeight.snug}",
            "type": "lineHeights"
          },
          "fontFamily": {
            "value": "{typography.fontFamily.body}",
            "type": "fontFamilies"
          }
        },
        "md": {
          "fontSize": {
            "value": "{typography.fontSize.14}",
            "type": "fontSizes"
          },
          "lineHeight": {
            "value": "{typography.lineHeight.snug}",
            "type": "lineHeights"
          },
          "fontFamily": {
            "value": "{typography.fontFamily.body}",
            "type": "fontFamilies"
          }
        },
        "sm": {
          "fontSize": {
            "value": "{typography.fontSize.12}",
            "type": "fontSizes"
          },
          "lineHeight": {
            "value": "{typography.lineHeight.snug}",
            "type": "lineHeights"
          },
          "fontFamily": {
            "value": "{typography.fontFamily.body}",
            "type": "fontFamilies"
          }
        },
        "caps": {
          "fontSize": {
            "value": "{typography.fontSize.12}",
            "type": "fontSizes"
          },
          "lineHeight": {
            "value": "{typography.lineHeight.snug}",
            "type": "lineHeights"
          },
          "fontFamily": {
            "value": "{typography.fontFamily.body}",
            "type": "fontFamilies"
          }
        }
      },
      "body": {
        "xl": {
          "fontSize": {
            "value": "{typography.fontSize.20}",
            "type": "fontSizes"
          },
          "lineHeight": {
            "value": "{typography.lineHeight.normal}",
            "type": "lineHeights"
          },
          "fontFamily": {
            "value": "{typography.fontFamily.body}",
            "type": "fontFamilies"
          }
        },
        "lg": {
          "fontSize": {
            "value": "{typography.fontSize.18}",
            "type": "fontSizes"
          },
          "lineHeight": {
            "value": "{typography.lineHeight.normal}",
            "type": "lineHeights"
          },
          "fontFamily": {
            "value": "{typography.fontFamily.body}",
            "type": "fontFamilies"
          }
        },
        "md": {
          "fontSize": {
            "value": "{typography.fontSize.16}",
            "type": "fontSizes"
          },
          "lineHeight": {
            "value": "{typography.lineHeight.normal}",
            "type": "lineHeights"
          },
          "fontFamily": {
            "value": "{typography.fontFamily.body}",
            "type": "fontFamilies"
          }
        },
        "sm": {
          "fontSize": {
            "value": "{typography.fontSize.14}",
            "type": "fontSizes"
          },
          "lineHeight": {
            "value": "{typography.lineHeight.normal}",
            "type": "lineHeights"
          },
          "fontFamily": {
            "value": "{typography.fontFamily.body}",
            "type": "fontFamilies"
          }
        },
        "xs": {
          "fontSize": {
            "value": "{typography.fontSize.12}",
            "type": "fontSizes"
          },
          "lineHeight": {
            "value": "{typography.lineHeight.normal}",
            "type": "lineHeights"
          },
          "fontFamily": {
            "value": "{typography.fontFamily.body}",
            "type": "fontFamilies"
          }
        }
      },
      "display": {
        "2xl": {
          "fontSize": {
            "value": "{typography.fontSize.64}",
            "type": "fontSizes"
          },
          "lineHeight": {
            "value": "{typography.lineHeight.none}",
            "type": "lineHeights"
          },
          "fontFamily": {
            "value": "{typography.fontFamily.display}",
            "type": "fontFamilies"
          }
        },
        "xl": {
          "fontSize": {
            "value": "{typography.fontSize.48}",
            "type": "fontSizes"
          },
          "lineHeight": {
            "value": "{typography.lineHeight.tight}",
            "type": "lineHeights"
          },
          "fontFamily": {
            "value": "{typography.fontFamily.display}",
            "type": "fontFamilies"
          }
        },
        "lg": {
          "fontSize": {
            "value": "{typography.fontSize.36}",
            "type": "fontSizes"
          },
          "lineHeight": {
            "value": "{typography.lineHeight.tight}",
            "type": "lineHeights"
          },
          "fontFamily": {
            "value": "{typography.fontFamily.display}",
            "type": "fontFamilies"
          }
        },
        "md": {
          "fontSize": {
            "value": "{typography.fontSize.28}",
            "type": "fontSizes"
          },
          "lineHeight": {
            "value": "{typography.lineHeight.snug}",
            "type": "lineHeights"
          },
          "fontFamily": {
            "value": "{typography.fontFamily.display}",
            "type": "fontFamilies"
          }
        },
        "sm": {
          "fontSize": {
            "value": "{typography.fontSize.24}",
            "type": "fontSizes"
          },
          "lineHeight": {
            "value": "{typography.lineHeight.snug}",
            "type": "lineHeights"
          },
          "fontFamily": {
            "value": "{typography.fontFamily.display}",
            "type": "fontFamilies"
          }
        }
      },
      "mono": {
        "xl": {
          "fontSize": {
            "value": "{typography.fontSize.32}",
            "type": "fontSizes"
          },
          "lineHeight": {
            "value": "{typography.lineHeight.none}",
            "type": "lineHeights"
          },
          "fontFamily": {
            "value": "{typography.fontFamily.mono}",
            "type": "fontFamilies"
          }
        },
        "lg": {
          "fontSize": {
            "value": "{typography.fontSize.24}",
            "type": "fontSizes"
          },
          "lineHeight": {
            "value": "{typography.lineHeight.none}",
            "type": "lineHeights"
          },
          "fontFamily": {
            "value": "{typography.fontFamily.mono}",
            "type": "fontFamilies"
          }
        },
        "md": {
          "fontSize": {
            "value": "{typography.fontSize.18}",
            "type": "fontSizes"
          },
          "lineHeight": {
            "value": "{typography.lineHeight.none}",
            "type": "lineHeights"
          },
          "fontFamily": {
            "value": "{typography.fontFamily.mono}",
            "type": "fontFamilies"
          }
        },
        "sm": {
          "fontSize": {
            "value": "{typography.fontSize.14}",
            "type": "fontSizes"
          },
          "lineHeight": {
            "value": "{typography.lineHeight.none}",
            "type": "lineHeights"
          },
          "fontFamily": {
            "value": "{typography.fontFamily.mono}",
            "type": "fontFamilies"
          }
        }
      }
    }
  },
  "components": {
    "button": {
      "primary": {
        "background": {
          "value": "{color.brand.brand-primary}",
          "type": "color"
        },
        "text": {
          "value": "{color.background.bg-base}",
          "type": "color"
        },
        "label": {
          "md": {
            "value": {
              "fontFamily": "{typography.label.md.fontFamily}",
              "fontWeight": "{typography.fontWeight.semiBold}"
            },
            "type": "typography"
          },
          "sm": {
            "value": {
              "fontFamily": "{typography.label.sm.fontFamily}",
              "fontWeight": "{typography.fontWeight.semiBold}"
            },
            "type": "typography"
          }
        },
        "height": {
          "md": {
            "value": "{spacing.9}",
            "type": "sizing"
          }
        }
      },
      "secondary": {
        "background": {
          "value": "{color.brand.brand-secondary}",
          "type": "color"
        },
        "text": {
          "value": "{color.brand.brand-primary}",
          "type": "color"
        }
      },
      "destructive": {
        "background": {
          "value": "{color.status.error}",
          "type": "color"
        },
        "text": {
          "value": "{color.neutral.0}",
          "type": "color"
        }
      },
      "disabled": {
        "background": {
          "value": "{color.background.bg-elevated}",
          "type": "color"
        },
        "text": {
          "value": "{color.text.text-muted}",
          "type": "color"
        }
      },
      "radius": {
        "value": "{radius.button-md}",
        "type": "borderRadius"
      }
    },
    "$extensions": {
      "studio": {
        "tokens": {
          "version": {
            "value": "1.0",
            "type": "other"
          },
          "figma": {
            "collection": {
              "value": "Components",
              "type": "other"
            },
            "mode": {
              "value": "dark",
              "type": "other"
            }
          }
        }
      }
    }
  },
  "$themes": [],
  "$metadata": {
    "tokenSetOrder": [
      "primitives",
      "semantic",
      "components"
    ]
  }
}